mlwcli/__init__.py
mlwcli/mlwcli.py
mlwcli-0.0.3.dist-info/LICENSE
mlwcli-0.0.3.dist-info/METADATA
mlwcli-0.0.3.dist-info/WHEEL
mlwcli-0.0.3.dist-info/entry_points.txt
mlwcli-0.0.3.dist-info/top_level.txt
mlwcli-0.0.3.dist-info/RECORD
