Metadata-Version: 2.1
Name: mlwcli
Version: 0.0.3
Summary: Command Line Interface for mlworks python package
Home-page: https://github.com/adelmofilho/mlw-cli
Author: Adelmo Filho
Author-email: adelmo.aguiar.filho@gmail.com
License: MIT
Keywords: mlworks,Python,projects,machine-learning,feature-engineering,modelling,data-science
Platform: UNKNOWN
Classifier: Programming Language :: Python :: 3 :: Only
Classifier: Programming Language :: Python :: 3
Classifier: Programming Language :: Python :: 3.6
Classifier: Programming Language :: Python :: 3.7
Classifier: Programming Language :: Python :: 3.8
Classifier: License :: OSI Approved :: MIT License
Classifier: Operating System :: OS Independent
Classifier: Development Status :: 1 - Planning
Classifier: Natural Language :: Portuguese (Brazilian)
Classifier: Topic :: Scientific/Engineering :: Artificial Intelligence
Requires-Python: >=3.6
